{
  "paging": {
    "page": 1,
    "count": 1,
    "maxPage": 1,
    "itemsTotal": 1
  },
  "packages": [
    {
      "id": "vlc.lgapp",
      "title": "VLC Media Player",
      "iconUri": "https://upload.wikimedia.org/wikipedia/commons/3/38/VLC_icon.png?20150202150351",
      "manifest": {
        "id": "vlc.lgapp",
        "version": "1.0.0",
        "type": "web",
        "title": "VLC Media Player",
        "iconUri": "https://upload.wikimedia.org/wikipedia/commons/3/38/VLC_icon.png?20150202150351",
        "sourceUrl": "https://github.com/DjVreditel/tiktok-webos",
        "rootRequired": false,
        "ipkUrl": "https://www.dropbox.com/scl/fi/c72fie28huks4nyh2d72r/com.hobbyistsoftware.vlcremote_1.1.0_all.ipk?rlkey=t5x0bc1s49v7eb07k2lj96mal&st=ddnl5sm3&dl=1",
        "ipkHash": {
          "sha256": "8d7f30ba594189f230ef93811d78c408798b1073d8dfde76c2c902968f39d69c"
        }
      },
      "shortDescription": "Unofficial VlC Player App for WebOS with extended features",
      "fullDescriptionUrl": "https://raw.githubusercontent.com/DjVreditel/tiktok-webos/main/HomebrewChannel/index.html"
    }
  ]
}
